mlprocessors/__init__.py
mlprocessors/core.py
mlprocessors/registry.py
mlprocessors/validators.py
mlprocessors-0.1.dist-info/METADATA
mlprocessors-0.1.dist-info/RECORD
mlprocessors-0.1.dist-info/WHEEL
mlprocessors-0.1.dist-info/top_level.txt
