Metadata-Version: 2.1
Name: mlprocessors
Version: 0.1
Summary: A Python framework for making MountainLab processor packages
Home-page: https://github.com/flatironinstitute/mlprocessors
Author: Witold Wysota
Author-email: wysota@wysota.org
License: UNKNOWN
Platform: UNKNOWN
Classifier: Programming Language :: Python :: 3
Classifier: License :: OSI Approved :: Apache Software License
Classifier: Operating System :: OS Independent
Requires-Dist: argparse
